lightning_bagua/__about__.py
lightning_bagua/__init__.py
lightning_bagua/environment.py
lightning_bagua/strategy.py
lightning_bagua-0.1.0.dist-info/LICENSE
lightning_bagua-0.1.0.dist-info/METADATA
lightning_bagua-0.1.0.dist-info/WHEEL
lightning_bagua-0.1.0.dist-info/top_level.txt
lightning_bagua-0.1.0.dist-info/RECORD
