Metadata-Version: 2.1
Name: lightning-bagua
Version: 0.1.0
Summary: Deep Learning Training Acceleration with Bagua and Lightning AI
Home-page: https://github.com/Lightning-AI/lightning-Bagua
Download-URL: https://github.com/Lightning-AI/lightning-Bagua
Author: Lightning-AI et al.
Author-email: name@lightning.ai
License: Apache-2.0
Project-URL: Bug Tracker, https://github.com/Lightning-AI/lightning-Bagua/issues
Project-URL: Documentation, https://lightning-ai.github.io/lightning-bagua/
Project-URL: Source Code, https://github.com/Lightning-AI/lightning-Bagua
Keywords: deep learning,pytorch,AI
Classifier: Environment :: Console
Classifier: Natural Language :: English
Classifier: Development Status :: 4 - Beta
Classifier: Intended Audience :: Developers
Classifier: Topic :: Scientific/Engineering :: Artificial Intelligence
Classifier: Topic :: Scientific/Engineering :: Information Analysis
Classifier: License :: OSI Approved :: Apache Software License
Classifier: Operating System :: OS Independent
Classifier: Programming Language :: Python :: 3
Classifier: Programming Language :: Python :: 3.8
Classifier: Programming Language :: Python :: 3.9
Classifier: Programming Language :: Python :: 3.10
Classifier: Programming Language :: Python :: 3.11
Requires-Python: >=3.8
License-File: LICENSE
Requires-Dist: lightning (>=2.0.0)
Requires-Dist: bagua-cuda116 (>=0.9.2)
